behave_testrail_reporter/__init__.py
behave_testrail_reporter/api.py
behave_testrail_reporter/testrail_reporter.py
behave_testrail_reporter-0.5.1.dist-info/LICENSE
behave_testrail_reporter-0.5.1.dist-info/METADATA
behave_testrail_reporter-0.5.1.dist-info/WHEEL
behave_testrail_reporter-0.5.1.dist-info/top_level.txt
behave_testrail_reporter-0.5.1.dist-info/RECORD
