Metadata-Version: 2.1
Name: behave-testrail-reporter
Version: 0.5.1
Summary: Behave library to integrate with Testrail API
Home-page: https://github.com/virtualstock/behave-testrail-reporter/
Author: Virtualstock
Author-email: development.team@virtualstock.co.uk
License: MIT
Keywords: Behave,Testrail,API,Test,BDD
Platform: UNKNOWN
Classifier: Programming Language :: Python :: 2.7
Classifier: Programming Language :: Python :: 3.4
Classifier: Programming Language :: Python :: 3.5
Classifier: Programming Language :: Python :: 3.6
License-File: LICENSE
Requires-Dist: jsonschema
Requires-Dist: behave
Requires-Dist: pyyaml
Requires-Dist: requests
